neo4j_tools/__init__.py
neo4j_tools/gds_db_load.py
neo4j_tools/gds_utils.py
neo4j_tools-0.5.1.dist-info/LICENSE
neo4j_tools-0.5.1.dist-info/METADATA
neo4j_tools-0.5.1.dist-info/WHEEL
neo4j_tools-0.5.1.dist-info/RECORD
